{"csid":"2005.018.1383","fields":{"descTechAttributeUnit":"","descInscriptionMethod":"","descTechAttributeMeasure":"","objectLevel":"","descInscriptionTransliteration":"","descInscriptionInterpretation":"","descContentPlace":"","descContentPeople":"","descContentOtherType":"","descContentNote":"","descCopyNumber":"","descContentPosition":"","objectTitle":"Souvenir books. Molly O' Play Book.","descInscriptionType":"","descContentActivity":"","descContentPerson":"","descInscriptionPosition":"","dateText":"","descComponentInfo":"","descDateText":"","objectName":"","descMaterialName":"","objectCurrency":"","descDateLatestSingleQualifier":"","objectNote":"","descMaterialSource":"","descDimension":"","descContentScript":"","descMaterialComponent":"","objectTitleType":"","descAge":"","descContentOther":"","descPhase":"","descContentEventName":"","dateAssociation":"","descMaterialNote":"","objectTitleTranslation":"","descDimensionUnit":"none","descContentDescription":"","comments":"","descMaterial":"","descContentOrganization":"","descDimensionPart":"","descDateAssociation":"","numberOfObjects":"1","descInscriptionTranslation":"","objectType":"","descAgeQualifier":"","descDateLatestSingleCertainty":"","descContentConcept":"","descEditionNumber":"","objectTitleLanguage":"","objectLanguage":"","descStatus":"","descColor":"","descTechAttribute":"","descDimensionValueQualifier":"","descContentObject":"","otherNumber":"","descContentMethod":"","datePeriod":"","descContentLanguage":"","descStyle":"","descContentEventNameType":"","objectSystem":"","descContentObjectType":"","descAgeUnit":"","distinguishingFeatures":"","descDateEarliestSingleCertainty":"","descPhysicalDescription":"","descComponentName":"","descInscriptionInscriber":"","descSex":"","descInscriptionContent":"","descDimensionValue":"","descDateEarliestSingleQualifier":"","descForm":"","description":"Souvenir book from the film Molly O'. Text on the cover reads, \"Molly O Play Book / The Story of Molly O as told in the \"Movies\" in a Series of Eighty Pictures with Titles / A Mack Sennett Production Starring Mabel Normand / Distributed by The Shotwell Manufacturing Company / Chicago, Brooklyn.\" The book includes eight pages, each with ten small, pasted card photographs. The first seventy photographs are captioned film stills, and the last ten are portraits of the film's stars, including Normand, George Nichols, Jack Mulhall, and Mack Sennett. ","descInscriptionScript":"","descDatePeriod":"","csid":"2005.018.1383","descInscriptionLanguage":"","accessionNumber":"2005.018.1383","descInscriptionDescription":"","responsibleDepartment":"none"},
    "relations": [
    ]}